LICENSE
MANIFEST.in
README.md
pyproject.toml
requirements.txt
setup.py
pyetrade/__init__.py
pyetrade/accounts.py
pyetrade/alerts.py
pyetrade/authorization.py
pyetrade/market.py
pyetrade/order.py
pyetrade.egg-info/PKG-INFO
pyetrade.egg-info/SOURCES.txt
pyetrade.egg-info/dependency_links.txt
pyetrade.egg-info/requires.txt
pyetrade.egg-info/top_level.txt
tests/test_accounts.py
tests/test_alerts.py
tests/test_authorization.py
tests/test_market.py
tests/test_order.py