Metadata-Version: 2.1
Name: pyetrade
Version: 2.1.1
Summary: eTrade API wrappers
Home-page: https://github.com/jessecooper/pyetrade
Author: Jesse Cooper
Author-email: jesse_cooper@codeholics.com
License: GPLv3
Keywords: etrade,pyetrade,stocks
Platform: any
Classifier: Development Status :: 4 - Beta
Classifier: Environment :: Console
Classifier: Intended Audience :: Developers
Classifier: Intended Audience :: Financial and Insurance Industry
Classifier: License :: OSI Approved :: GNU General Public License v3 or later (GPLv3+)
Classifier: Natural Language :: English
Classifier: Programming Language :: Python :: 3
Classifier: Programming Language :: Python :: 3.9
Classifier: Programming Language :: Python :: 3.10
Classifier: Programming Language :: Python :: 3.11
Classifier: Programming Language :: Python :: 3.12
Classifier: Topic :: Software Development :: Libraries
License-File: LICENSE
Requires-Dist: certifi==2024.8.30; python_version >= "3.9" and python_version < "4.0"
Requires-Dist: charset-normalizer==3.4.0; python_version >= "3.9" and python_version < "4.0"
Requires-Dist: idna==3.10; python_version >= "3.9" and python_version < "4.0"
Requires-Dist: jxmlease==1.0.3; python_version >= "3.9" and python_version < "4.0"
Requires-Dist: oauthlib==3.2.2; python_version >= "3.9" and python_version < "4.0"
Requires-Dist: python-dateutil==2.9.0.post0; python_version >= "3.9" and python_version < "4.0"
Requires-Dist: requests-oauthlib==2.0.0; python_version >= "3.9" and python_version < "4.0"
Requires-Dist: requests==2.32.3; python_version >= "3.9" and python_version < "4.0"
Requires-Dist: six==1.16.0; python_version >= "3.9" and python_version < "4.0"
Requires-Dist: urllib3==1.26.19; python_version >= "3.9" and python_version < "4.0"
Requires-Dist: xmltodict==0.13.0; python_version >= "3.9" and python_version < "4.0"
